sapiensknn/__01010101.py
sapiensknn/__init__.py
sapiensknn/core.py
sapiensknn/sapiensknn.py
sapiensknn-1.0.3.dist-info/LICENSE.txt
sapiensknn-1.0.3.dist-info/METADATA
sapiensknn-1.0.3.dist-info/WHEEL
sapiensknn-1.0.3.dist-info/top_level.txt
sapiensknn-1.0.3.dist-info/RECORD
