Metadata-Version: 2.1
Name: sapiensknn
Version: 1.0.3
Summary: SapiensKNN (K-Nearest Neighbors) is an algorithm for classification and regression that returns the result based on the Euclidean distance between the input values.
Home-page: https://github.com/sapiens-technology/SapiensKNN
Author: SAPIENS TECHNOLOGY
License: Proprietary Software
Project-URL: Source code, https://github.com/sapiens-technology/SapiensKNN
Project-URL: Download, https://github.com/sapiens-technology/SapiensKNN/archive/refs/heads/main.zip
Keywords: Sapiens,Artificial Intelligence,Machine Learning,Data Science,AI,ML,KNN,K-Nearest Neighbors
License-File: LICENSE.txt
